examples/analytics/__init__.py
examples/analytics/metric_example.py
examples/catalog/__init__.py
examples/catalog/model_example.py
examples/collection/__init__.py
examples/collection/collection_example.py
examples/library/__init__.py
examples/library/library_example.py
examples/marketplace/__init__.py
examples/marketplace/marketplace_item_example.py
examples/marketplace/marketplace_listing_example.py
examples/media/__init__.py
examples/media/associated_media_example.py
examples/media/thumbnail_media_example.py
examples/metamodel/__init__.py
examples/metamodel/metamodel_example.py
examples/metamodel/metamodel_rating_example.py
examples/model/__init__.py
examples/model/model_example.py
examples/notifications/__init__.py
examples/notifications/notification_example.py
examples/notifications/notification_settings_example.py
examples/storage/__init__.py
examples/storage/storage_connection_example.py
examples/storage/storage_provider_config_example.py
examples/subscription/__init__.py
examples/subscription/subscription_example.py
examples/tag/__init__.py
examples/tag/tag_example.py
examples/texture/__init__.py
examples/texture/texture_example.py
examples/user/__init__.py
examples/user/user_example.py
mesh_sync_common/__init__.py
mesh_sync_common/py.typed
mesh_sync_common/domain/analytics/__init__.py
mesh_sync_common/domain/analytics/metric.py
mesh_sync_common/domain/catalog/__init__.py
mesh_sync_common/domain/catalog/model.py
mesh_sync_common/domain/collection/__init__.py
mesh_sync_common/domain/collection/collection.py
mesh_sync_common/domain/library/__init__.py
mesh_sync_common/domain/library/library.py
mesh_sync_common/domain/marketplace/__init__.py
mesh_sync_common/domain/marketplace/marketplace_item.py
mesh_sync_common/domain/marketplace/marketplace_listing.py
mesh_sync_common/domain/media/__init__.py
mesh_sync_common/domain/media/associated_media.py
mesh_sync_common/domain/media/thumbnail_media.py
mesh_sync_common/domain/metamodel/__init__.py
mesh_sync_core_common_lib-0.3.1.dist-info/METADATA
mesh_sync_core_common_lib-0.3.1.dist-info/WHEEL
mesh_sync_core_common_lib-0.3.1.dist-info/top_level.txt
mesh_sync_core_common_lib-0.3.1.dist-info/RECORD
