Metadata-Version: 2.4
Name: mesh-sync-core-common-lib
Version: 0.3.1
Summary: Shared domain models and types for MeshSync platform
Author-email: MeshSync Team <dev@meshsync.io>
License: MIT
Project-URL: Homepage, https://github.com/Mesh-Sync/core-common-lib
Project-URL: Repository, https://github.com/Mesh-Sync/core-common-lib.git
Project-URL: Documentation, https://docs.meshsync.io/core-common-lib
Project-URL: Issues, https://github.com/Mesh-Sync/core-common-lib/issues
Keywords: mesh-sync,domain-driven-design,ddd,shared-kernel,value-objects,aggregates,sqlalchemy
Classifier: Development Status :: 3 - Alpha
Classifier: Intended Audience :: Developers
Classifier: License :: OSI Approved :: MIT License
Classifier: Programming Language :: Python :: 3
Classifier: Programming Language :: Python :: 3.11
Classifier: Programming Language :: Python :: 3.12
Classifier: Programming Language :: Python :: 3.13
Classifier: Topic :: Software Development :: Libraries :: Python Modules
Classifier: Typing :: Typed
Requires-Python: >=3.11
Requires-Dist: sqlalchemy<3.0.0,>=2.0.0
Requires-Dist: pydantic<3.0.0,>=2.0.0
Provides-Extra: dev
Requires-Dist: pytest>=8.0.0; extra == "dev"
Requires-Dist: pytest-cov>=4.0.0; extra == "dev"
Requires-Dist: mypy>=1.8.0; extra == "dev"
Requires-Dist: ruff>=0.2.0; extra == "dev"
